nadeocr/__main__.py
nadeocr/GUI/functions/google_provider.py
nadeocr/GUI/functions/keyboard_manager.py
nadeocr/GUI/functions/mangaocr_provider.py
nadeocr/GUI/functions/utils/__init__.py
nadeocr/GUI/functions/utils/extra.py
nadeocr/GUI/functions/utils/worker.py
nadeocr/GUI/widgets/crop_widget.py
nadeocr/GUI/widgets/input_hotkey_widget.py
nadeocr/GUI/widgets/options_widget.py
nadeocr/GUI/widgets/popup_widget.py
nadeocr/GUI/widgets/toast_widget.py
nadeocr/GUI/widgets/tray_widget.py
nadeocr/resources/assets/icon.ico
nadeocr/resources/assets/icon_loading.ico
nadeocr/resources/hooks/hook-grpc.py
nadeocr/resources/hooks/hooks-gcloud.py
nadeocr/settings/config.ini
NadeOCR-1.0.1.3.dist-info/LICENSE
NadeOCR-1.0.1.3.dist-info/METADATA
NadeOCR-1.0.1.3.dist-info/WHEEL
NadeOCR-1.0.1.3.dist-info/entry_points.txt
NadeOCR-1.0.1.3.dist-info/top_level.txt
NadeOCR-1.0.1.3.dist-info/RECORD
