Metadata-Version: 2.1
Name: NadeOCR
Version: 1.0.1.3
Author: Natsume
Author-email: jonathan.197ariza@gmail.com
License: GPLv3
License-File: LICENSE
Requires-Dist: google-cloud-vision
Requires-Dist: manga-ocr
Requires-Dist: pynput
Requires-Dist: pyperclip
Requires-Dist: PyQt5
Requires-Dist: PySide6
Requires-Dist: screeninfo
